imdb/__init__.py
imdb/__main__.py
imdb/api.py
tdm_bridge14-0.1.1.dist-info/LICENSE
tdm_bridge14-0.1.1.dist-info/METADATA
tdm_bridge14-0.1.1.dist-info/WHEEL
tdm_bridge14-0.1.1.dist-info/entry_points.txt
tdm_bridge14-0.1.1.dist-info/top_level.txt
tdm_bridge14-0.1.1.dist-info/RECORD
